tests/__init__.py
tests/build_output_assertions.py
tests/test_async.py
tests/test_audio_compositions.py
tests/test_background_music.py
tests/test_building_strategies.py
tests/test_ci_providers_health_checks.py
tests/test_composite_video.py
tests/test_fake_ml_gateway.py
tests/test_ffmpeg_wrapper.py
tests/test_filetools.py
tests/test_imported_video.py
tests/test_model_providers.py
tests/test_prompt.py
tests/test_prompt_based_video.py
tests/test_prompt_building_handlers.py
tests/test_prompt_factory.py
tests/test_raw_image_based_video.py
tests/test_raw_text_based_video.py
tests/test_replicate_wrapper.py
tests/test_subtitles_extractors.py
tests/test_video.py
tests/test_video_building_handlers.py
tests/test_video_file_names.py
tests/test_video_metadata.py
tests/testing_medias.py
tests/testing_tools.py
vikit/__init__.py
vikit/common/GeneralBuildSettings.py
vikit/common/config.py
vikit/common/context_managers.py
vikit/common/decorators.py
vikit/common/file_tools.py
vikit/common/handler.py
vikit/common/secrets.py
vikit/gateways/ML_models_gateway.py
vikit/gateways/ML_models_gateway_factory.py
vikit/gateways/elevenlabs_gateway.py
vikit/gateways/fake_ML_models_gateway.py
vikit/gateways/replicate_gateway.py
vikit/gateways/vikit_gateway.py
vikit/music_building_context.py
vikit/prompt/building/handlers/prompt_by_keywords_handler.py
vikit/prompt/building/handlers/prompt_by_raw_usertext_handler.py
vikit/prompt/image_prompt.py
vikit/prompt/prompt.py
vikit/prompt/prompt_build_settings.py
vikit/prompt/prompt_cleaning.py
vikit/prompt/prompt_factory.py
vikit/prompt/recorded_prompt.py
vikit/prompt/recorded_prompt_subtitles_extractor.py
vikit/prompt/subtitle_extractor.py
vikit/video/building/build_order.py
vikit/video/building/handlers/default_bg_music_and_audio_merging_handler.py
vikit/video/building/handlers/gen_read_aloud_prompt_and_audio_merging_handler.py
vikit/video/building/handlers/generate_music_and_merge_handler.py
vikit/video/building/handlers/interpolation_handler.py
vikit_sdk-0.1.22.dist-info/LICENSE
vikit_sdk-0.1.22.dist-info/METADATA
vikit_sdk-0.1.22.dist-info/WHEEL
vikit_sdk-0.1.22.dist-info/RECORD
